lyrebird/__init__.py
lyrebird/__main__.py
lyrebird/cli.py
lyrebird_cli-0.1.0.dist-info/METADATA
lyrebird_cli-0.1.0.dist-info/WHEEL
lyrebird_cli-0.1.0.dist-info/entry_points.txt
lyrebird_cli-0.1.0.dist-info/top_level.txt
lyrebird_cli-0.1.0.dist-info/RECORD
