Metadata-Version: 2.4
Name: lyrebird-cli
Version: 0.1.0
Summary: 🐦 Lyrebird CLI: AI-Powered Coding Assistant in Your Terminal
Author: Muneeb Mahfooz Abbasi
Author-email: Muneeb Mahfooz Abbasi <abbasimuneeb54@gmail.com>
License: Apache-2.0
Project-URL: Homepage, https://github.com/muneebabbasi10/lyrebird-cli
Project-URL: Documentation, https://github.com/muneebabbasi10/lyrebird-cli#readme
Project-URL: Repository, https://github.com/muneebabbasi10/lyrebird-cli
Project-URL: Bug Tracker, https://github.com/yourusername/lyrebird-cli/issues
Keywords: cli,ai,coding,assistant,llm,openai,deepseek
Classifier: Development Status :: 4 - Beta
Classifier: Intended Audience :: Developers
Classifier: License :: OSI Approved :: Apache Software License
Classifier: Operating System :: OS Independent
Classifier: Programming Language :: Python :: 3
Classifier: Programming Language :: Python :: 3.8
Classifier: Programming Language :: Python :: 3.9
Classifier: Programming Language :: Python :: 3.10
Classifier: Programming Language :: Python :: 3.11
Classifier: Programming Language :: Python :: 3.12
Classifier: Topic :: Software Development :: Code Generators
Classifier: Topic :: Text Processing :: Linguistic
Requires-Python: >=3.8
Requires-Dist: typer[all]>=0.9.0
Requires-Dist: openai>=1.3.0
Requires-Dist: rich>=13.0.0
Requires-Dist: python-dotenv>=1.0.0
Requires-Dist: requests>=2.28.0
Provides-Extra: dev
Requires-Dist: pytest>=7.0.0; extra == "dev"
Requires-Dist: pytest-cov>=4.0.0; extra == "dev"
Requires-Dist: black>=23.0.0; extra == "dev"
Requires-Dist: flake8>=6.0.0; extra == "dev"
Requires-Dist: mypy>=1.0.0; extra == "dev"
Requires-Dist: pre-commit>=3.0.0; extra == "dev"
